[
  {
    "category": "Основное",
    "rules": [
      {
        "id": "1.1",
        "title": "Общие положения",
        "text": "Данный свод правил составлен представителем проекта BeeHive и действителен на всех игровых режимах проекта BeeHive. Незнание правил не освобождает нарушителя от ответственности, а также может усугубить наказание."
      },
      {
        "id": "1.2",
        "title": "Изменения правил",
        "text": "Незначительные изменения в правилах сервера могут меняться без уведомления, а о крупных изменениях администрация сообщает в социальных сетях."
      },
      {
        "id": "1.3",
        "title": "Реклама",
        "text": "Запрещена любая реклама любых ресурсов на всех наших серверах."
      },
      {
        "id": "1.4",
        "title": "Политика и религия",
        "text": "Запрещено поднятие политических и религиозных тем и споров на наших серверах."
      }
    ]
  },
  {
    "category": "Игровой процесс",
    "rules": [
      {
        "id": "2.1",
        "title": "Постороннее ПО",
        "text": "Запрещено использовать постороннее ПО (читы, программы). Наказание: бан на 30 дней."
      },
      {
        "id": "2.2",
        "title": "Ресурспаки",
        "text": "Запрещено использовать ресурспаки, дающие преимущество (например, x-ray). Наказание: бан на 7 дней."
      },
      {
        "id": "2.3",
        "title": "Дюпы",
        "text": "Использование каких-либо дюпов запрещено. Наказание: бан на 15 дней."
      },
      {
        "id": "2.4",
        "title": "Лаг-машины",
        "text": "Постройка лаг-машин строго запрещена. Наказание: перманентный бан."
      }
    ]
  },
  {
    "category": "Общение",
    "rules": [
      {
        "id": "3.1",
        "title": "Оскорбления",
        "text": "Запрещено оскорбление игроков проекта, их родственников, а также администрации сервера. Наказание: мут на 1 час."
      },
      {
        "id": "3.2",
        "title": "Спам",
        "text": "Запрещено спамить в чат. Наказание: мут на 30 минут."
      },
      {
        "id": "3.3",
        "title": "Лексика",
        "text": "Запрещено использовать нецензурную лексику в чате или писать на табличках. Наказание: бан на 1 день."
      },
      {
        "id": "3.4",
        "title": "Символика",
        "text": "Запрещено строить неприличные жесты или символику. Наказание: бан на 2 дня."
      }
    ]
  },
  {
    "category": "Лайфстайл",
    "rules": [
      {
        "id": "4.1",
        "title": "Твинки",
        "text": "Запрещено использовать свои твинки для получения сердец. Наказание: бан на 30 дней."
      },
      {
        "id": "4.2",
        "title": "Территория спавна",
        "text": "Запрещено портить территорию спавна (в радиусе 150 блоков). Наказание: бан на 2 дня."
      },
      {
        "id": "4.3",
        "title": "Новички",
        "text": "Запрещено без причины убивать новичков (кроме самообороны). Наказание: бан на 4 часа."
      }
    ]
  }
]
